dirdesc/__init__.py
dirdesc/__version__.py
dirdesc/dirdesc.py
dirdesc-0.1.1.dist-info/entry_points.txt
dirdesc-0.1.1.dist-info/WHEEL
dirdesc-0.1.1.dist-info/METADATA
dirdesc-0.1.1.dist-info/RECORD
