Metadata-Version: 2.1
Name: dirdesc
Version: 0.1.1
Summary: Generate an annotated directory tree description
License: MIT
Author: Noah Pendleton
Requires-Python: >=3.7.2,<4.0.0
Classifier: License :: OSI Approved :: MIT License
Classifier: Programming Language :: Python :: 3
Classifier: Programming Language :: Python :: 3.10
Classifier: Programming Language :: Python :: 3.8
Classifier: Programming Language :: Python :: 3.9
Requires-Dist: PyYAML (>=6.0,<7.0)
Requires-Dist: click (>=8.1.3,<9.0.0)
Requires-Dist: mypy (>=0.971,<0.972)
Requires-Dist: pylint (>=2.14.5,<3.0.0)
Requires-Dist: rich (>=12.5.1,<13.0.0)
Requires-Dist: types-PyYAML (>=6.0.11,<7.0.0)
